Metadata-Version: 2.1
Name: NumbersHelper
Version: 1.1.3
Summary: Helper functions for working
Home-page: https://github.com/Numbers-Technologies
Author-email: blcklptn@gmail.com
License: UNKNOWN
Platform: UNKNOWN
